LICENSE
README.md
setup.py
altair_easeviz/__init__.py
altair_easeviz/description_generator.py
altair_easeviz/themes.py
altair_easeviz/tokens.py
altair_easeviz/types_theme.py
altair_easeviz/utils.py
altair_easeviz.egg-info/PKG-INFO
altair_easeviz.egg-info/SOURCES.txt
altair_easeviz.egg-info/dependency_links.txt
altair_easeviz.egg-info/entry_points.txt
altair_easeviz.egg-info/requires.txt
altair_easeviz.egg-info/top_level.txt
altair_easeviz/models/__init__.py
altair_easeviz/models/models_axis.py
altair_easeviz/models/models_config.py
altair_easeviz/models/models_header.py
altair_easeviz/models/models_legend.py
altair_easeviz/models/models_mark.py
altair_easeviz/models/models_range.py
altair_easeviz/models/models_theme.py
altair_easeviz/models/models_title.py
altair_easeviz/models/models_view.py
altair_easeviz/templates/__init__.py
altair_easeviz/templates/accessible_template.py
altair_easeviz/templates/r_code_templates.py