Metadata-Version: 2.1
Name: altair-easeviz
Version: 1.0
Summary: Accesible themes and functions to create accessible graph for Altair
Home-page: https://miguelub.github.io/altair-easeviz/
Author: Miguel Huayllas
Author-email: mhuaylch10@alumnes.ub.edu
License: MIT
License-File: LICENSE
